godot_ouroboros/__init__.py
godot_ouroboros-0.1.0.dist-info/entry_points.txt
godot_ouroboros-0.1.0.dist-info/METADATA
godot_ouroboros-0.1.0.dist-info/WHEEL
godot_ouroboros-0.1.0.dist-info/RECORD
