Metadata-Version: 2.1
Name: godot-ouroboros
Version: 0.1.0
Summary: 
Author: Jonathan Crum
Author-email: jcrum@theobogroup.com
Requires-Python: >=3.11,<4.0
Classifier: Programming Language :: Python :: 3
Classifier: Programming Language :: Python :: 3.11
Requires-Dist: python-dotenv (>=0.21.1,<0.22.0)
